recOrder/base/__init__.py
recOrder/base/acquisition/__init__.py
recOrder/base/acquisition/_acquisition_base.py
recOrder/base/acquisition/tests/__init__.py
recOrder/base/acquisition/tests/acquisition_base_tests.py
recOrder/base/analysis/__init__.py
recOrder/base/analysis/_analyze_base.py
recOrder/base/analysis/tests/AnalyzeBase_tests.py
recOrder/base/analysis/tests/__init__.py
recOrder/base/microscope/__init__.py
recOrder/base/microscope/coms.py
recOrder/base/program/BuildProgram.py
recOrder/base/program/__init__.py
recOrder/base/utils/QThreader.py
recOrder/base/utils/__init__.py
recOrder/base/visualization/__init__.py
recOrder/base/visualization/_visualize_base.py
recOrder_base_test-0.0.1.dist-info/METADATA
recOrder_base_test-0.0.1.dist-info/WHEEL
recOrder_base_test-0.0.1.dist-info/top_level.txt
recOrder_base_test-0.0.1.dist-info/RECORD
