Metadata-Version: 2.1
Name: recOrder-base-test
Version: 0.0.1
Summary: Framework to enable acquisition, analysis, visualization of computational microscopy workflows
Home-page: https://github.com/czbiohub/recOrder
Author: Bryant Chhun
Author-email: bchhun@gmail.com
License: Chan Zuckerberg Biohub Software License
Platform: UNKNOWN
Classifier: License :: OSI Approved :: BSD License
Classifier: Programming Language :: Python
Classifier: Programming Language :: Python :: 3 :: Only
Classifier: Programming Language :: Python :: 3.6
Classifier: Programming Language :: Python :: 3.7
Classifier: Topic :: Scientific/Engineering
Classifier: Topic :: Scientific/Engineering :: Visualization
Classifier: Topic :: Scientific/Engineering :: Information Analysis
Classifier: Topic :: Scientific/Engineering :: Bio-Informatics
Classifier: Topic :: Utilities
Classifier: Operating System :: Microsoft :: Windows
Classifier: Operating System :: POSIX
Classifier: Operating System :: Unix
Classifier: Operating System :: MacOS
Requires-Python: >=3.6
Requires-Dist: PyQt5 (>=5.13.0)
